{
  "id": "da-0006",
  "title": "SOPHIA：複数施設の肥満コホートデータを活用した大規模層別化研究",
  "region": "国外",
  "domain": "医療",
  "organization": "SOPHIA project / DataSHIELD consortium",
  "usecase_category": [
    "R&D"
  ],
  "technology_category": [
    "distributed_analytics"
  ],
  "review_status": "flagged",
  "summary": "肥満研究では、複数の医療機関や研究施設に分散するコホートデータを統合的に解析する必要があるが、個人レベルの医療データを施設間で移動させることは倫理的・法的に困難だった。単施設のデータだけでは十分なサンプルサイズが確保できず、肥満の層別化やバイオマーカー発見の検出力に限界があった。",
  "value_proposition": "DataSHIELD基盤を用いて各施設にRサーバーを設置し、個人データを移動させずに統計解析コマンドを分散実行する方式を採用した。これにより、複数の肥満コホートデータを仮想的に統合し、大規模な層別化・バイオマーカー研究を実施可能にした。",
  "privacy_enhancement_method": "DataSHIELD（Rベース分散解析フレームワーク）",
  "safety_assurance_method": "各施設のRサーバーでローカル実行、要約統計のみ返送",
  "utility_evaluation_method": "従来の単施設研究との比較によるサンプルサイズ・検出力の向上",
  "tags": [
    "DataSHIELD",
    "SOPHIA",
    "肥満",
    "Horizon 2020"
  ],
  "sources": [
    {
      "source_type": "web",
      "title": "SOPHIA project",
      "url": "https://imisophia.eu/",
      "note": "プロジェクト概要"
    }
  ],
  "figures": [
    {
      "type": "data_flow",
      "title": "DataSHIELD/SOPHIAのデータフロー",
      "note": "",
      "data": {
        "nodes": [
          {
            "id": "s1",
            "label": "複数の肥満コホートデータ",
            "category": "source"
          },
          {
            "id": "s2",
            "label": "個人データ移動の制約",
            "category": "constraint"
          },
          {
            "id": "p1",
            "label": "DataSHIELDによる分散解析実行",
            "category": "process"
          },
          {
            "id": "a1",
            "label": "肥満の層別化・バイオマーカー分析",
            "category": "application"
          },
          {
            "id": "a2",
            "label": "大規模な層別化研究の実現",
            "category": "outcome"
          }
        ],
        "edges": [
          {
            "from": "s1",
            "to": "p1",
            "label": "コホートデータ"
          },
          {
            "from": "s2",
            "to": "p1",
            "label": "データ移動なし"
          },
          {
            "from": "p1",
            "to": "a1",
            "label": "要約統計量"
          },
          {
            "from": "a1",
            "to": "a2",
            "label": "層別化結果"
          }
        ]
      }
    }
  ],
  "editorial_notes": [
    "出典URL（imisophia.eu）が接続拒否でアクセス不能。出典差し替え必須"
  ],
  "status": "seed",
  "occurred_at": null,
  "created_at": "2026-03-09T00:00:00.000Z",
  "updated_at": "2026-03-09T00:00:00.000Z"
}
